BoxArchive-0.0.1.dist-info/METADATA
BoxArchive-0.0.1.dist-info/RECORD
BoxArchive-0.0.1.dist-info/WHEEL
BoxArchive-0.0.1.dist-info/entry_points.txt
BoxArchive-0.0.1.dist-info/top_level.txt
box_archive/__init__.py
box_archive/cli.py
