Metadata-Version: 2.1
Name: BoxArchive
Version: 0.0.1
Summary: BoxArchive lets you archive files and folders on your system to your Box account
Home-page: https://github.com/sushshring/BoxArchive
Author: Sushrut Shringarputale
Author-email: contact@sushshring.com
License: BSD
Platform: any
Classifier: Development Status :: 4 - Beta
Classifier: Environment :: Console
Classifier: Intended Audience :: Developers
Classifier: License :: OSI Approved :: BSD License
Classifier: Operating System :: POSIX
Classifier: Operating System :: MacOS
Classifier: Operating System :: Unix
Classifier: Operating System :: Microsoft :: Windows
Classifier: Programming Language :: Python
Classifier: Programming Language :: Python :: 2
Classifier: Programming Language :: Python :: 3
Classifier: Topic :: Software Development :: Libraries :: Python Modules
Requires-Dist: click
